deid/__init__.py
deid/version.py
deid/config/__init__.py
deid/config/standards.py
deid/config/utils.py
deid/data/__init__.py
deid/data/deid.dicom
deid/data/deid.dicom.ultrasound
deid/data/deid.dicom.xray.chest
deid/dicom/__init__.py
deid/dicom/config.json
deid/dicom/fields.py
deid/dicom/filter.py
deid/dicom/groups.py
deid/dicom/header.py
deid/dicom/parser.py
deid/dicom/tags.py
deid/dicom/utils.py
deid/dicom/validate.py
deid/dicom/actions/__init__.py
deid/dicom/actions/jitter.py
deid/dicom/actions/uids.py
deid/dicom/pixels/__init__.py
deid/dicom/pixels/clean.py
deid/dicom/pixels/detect.py
deid/logger/__init__.py
deid/logger/message.py
deid/logger/progress.py
deid/main/__init__.py
deid/main/identifiers.py
deid/main/inspect.py
deid/tests/Xtest_dicom_header.py
deid/tests/__init__.py
deid/tests/common.py
deid/tests/test_action_interaction.py
deid/tests/test_blank_action.py
deid/tests/test_clean.py
deid/tests/test_clean_pixel_dimensions.py
deid/tests/test_cli.py
deid/tests/test_config.py
deid/tests/test_data.py
deid/tests/test_deid_recipe.py
deid/tests/test_dicom_fields.py
deid/tests/test_dicom_funcs.py
deid/tests/test_dicom_groups.py
deid/tests/test_dicom_pixels.py
deid/tests/test_dicom_tags.py
deid/tests/test_dicom_utils.py
deid/tests/test_file_meta.py
deid/tests/test_filter_detect.py
deid/tests/test_nested_dicom_fields.py
deid/tests/test_remove_action.py
deid/tests/test_replace_action.py
deid/tests/test_replace_identifiers.py
deid/tests/test_sequence_blank.py
deid/tests/test_sequence_jitter.py
deid/tests/test_sequence_remove.py
deid/tests/test_sequence_replace.py
deid/tests/test_utils.py
deid/tests/test_utils_files.py
deid/utils/__init__.py
deid/utils/actions.py
deid/utils/fileio.py
deid-0.4.11.dist-info/AUTHORS.md
deid-0.4.11.dist-info/LICENSE
deid-0.4.11.dist-info/METADATA
deid-0.4.11.dist-info/WHEEL
deid-0.4.11.dist-info/entry_points.txt
deid-0.4.11.dist-info/top_level.txt
deid-0.4.11.dist-info/RECORD
